zentropi/__init__.py
zentropi/__main__.py
zentropi/cli.py
zentropi-2020.0.1.dist-info/AUTHORS.rst
zentropi-2020.0.1.dist-info/LICENSE
zentropi-2020.0.1.dist-info/METADATA
zentropi-2020.0.1.dist-info/WHEEL
zentropi-2020.0.1.dist-info/entry_points.txt
zentropi-2020.0.1.dist-info/top_level.txt
zentropi-2020.0.1.dist-info/RECORD
