Metadata-Version: 2.1
Name: zentropi
Version: 2020.0.1
Summary: Zentropi Agent Framework: Script Your World
Home-page: https://github.com/zentropi/python-zentropi
Author: Harshad Sharma
Author-email: harshad@sharma.io
License: BSD-3-Clause
Project-URL: Documentation, https://zentropi.readthedocs.io/
Project-URL: Changelog, https://zentropi.readthedocs.io/en/latest/changelog.html
Project-URL: Issue Tracker, https://github.com/zentropi/python-zentropi/issues
Platform: UNKNOWN
Classifier: Development Status :: 1 - Planning
Classifier: Intended Audience :: Developers
Classifier: License :: OSI Approved :: BSD License
Classifier: Operating System :: Unix
Classifier: Operating System :: POSIX
Classifier: Operating System :: Microsoft :: Windows
Classifier: Programming Language :: Python
Classifier: Programming Language :: Python :: 3
Classifier: Programming Language :: Python :: 3.7
Classifier: Programming Language :: Python :: Implementation :: CPython
Classifier: Topic :: Utilities
Classifier: Topic :: Communications
Requires-Python: >=2.7, !=3.0.*, !=3.1.*, !=3.2.*, !=3.3.*, !=3.4.*
Requires-Dist: click
